{
  "generated_at": "2026-06-29T09:04:45.383675Z",
  "rates_by_day": {
    "Today": {
      "Comfort Inn Beckley": {
        "primary": {
          "price": 110,
          "category": "public_refundable",
          "basis": "nightly",
          "source": "properties"
        },
        "ranges": {
          "public_refundable": {
            "low": 110,
            "high": 142
          }
        },
        "expedia": null,
        "brand_strict": true,
        "debug": {
          "raw_file": "Comfort_Inn_Beckley_2026-06-29_addr_ok_20260629T090345Z.json",
          "provider_ctx": "Comfort Inn Beckley",
          "picked_from": "properties"
        }
      },
      "Courtyard Beckley": {
        "primary": {
          "price": 135,
          "category": "public_refundable",
          "basis": "nightly",
          "source": "properties"
        },
        "ranges": {
          "public_refundable": {
            "low": 135,
            "high": 152
          }
        },
        "expedia": null,
        "brand_strict": false,
        "debug": {
          "raw_file": "Courtyard_Beckley_2026-06-29_addr_ok_20260629T090351Z.json",
          "provider_ctx": "Straightforward hotel offering contemporary rooms & a courtyard with a fire pit, plus free WiFi. | Courtyard by Marriott Beckley",
          "picked_from": "properties"
        }
      },
      "Hampton Inn Beckley": "N/A",
      "Tru by Hilton Beckley": "N/A",
      "Fairfield Inn Beckley": {
        "primary": {
          "price": 142,
          "category": "public_refundable",
          "basis": "nightly",
          "source": "ads"
        },
        "ranges": {
          "public_refundable": {
            "low": 142,
            "high": 142
          }
        },
        "expedia": null,
        "brand_strict": false,
        "debug": {
          "raw_file": "Fairfield_Inn_Beckley_2026-06-29_addr_ok_20260629T090400Z.json",
          "provider_ctx": "Comfort Inn Beckley | Comfort Inn Beckley",
          "picked_from": "ads"
        }
      },
      "Best Western Beckley": {
        "primary": {
          "price": 149,
          "category": "public_refundable",
          "basis": "nightly",
          "source": "ads"
        },
        "ranges": {
          "public_refundable": {
            "low": 149,
            "high": 149
          }
        },
        "expedia": null,
        "brand_strict": false,
        "debug": {
          "raw_file": "Best_Western_Beckley_2026-06-29_addr_ok_20260629T090402Z.json",
          "provider_ctx": "Booking.com | Best Western Plus Beckley Inn",
          "picked_from": "ads"
        }
      },
      "Country Inn Beckley": {
        "primary": {
          "price": 142,
          "category": "public_refundable",
          "basis": "nightly",
          "source": "ads"
        },
        "ranges": {
          "public_refundable": {
            "low": 142,
            "high": 142
          }
        },
        "expedia": null,
        "brand_strict": false,
        "debug": {
          "raw_file": "Country_Inn_Beckley_2026-06-29_addr_ok_20260629T090404Z.json",
          "provider_ctx": "Comfort Inn Beckley | Comfort Inn Beckley",
          "picked_from": "ads"
        }
      }
    },
    "Tomorrow": {
      "Comfort Inn Beckley": {
        "primary": {
          "price": 115,
          "category": "public_refundable",
          "basis": "nightly",
          "source": "properties"
        },
        "ranges": {
          "public_refundable": {
            "low": 115,
            "high": 139
          }
        },
        "expedia": null,
        "brand_strict": true,
        "debug": {
          "raw_file": "Comfort_Inn_Beckley_2026-06-30_addr_ok_20260629T090408Z.json",
          "provider_ctx": "Comfort Inn Beckley",
          "picked_from": "properties"
        }
      },
      "Courtyard Beckley": {
        "primary": {
          "price": 141,
          "category": "public_refundable",
          "basis": "nightly",
          "source": "properties"
        },
        "ranges": {
          "public_refundable": {
            "low": 141,
            "high": 179
          }
        },
        "expedia": null,
        "brand_strict": false,
        "debug": {
          "raw_file": "Courtyard_Beckley_2026-06-30_addr_ok_20260629T090410Z.json",
          "provider_ctx": "Straightforward hotel offering contemporary rooms & a courtyard with a fire pit, plus free WiFi. | Courtyard by Marriott Beckley",
          "picked_from": "properties"
        }
      },
      "Hampton Inn Beckley": "N/A",
      "Tru by Hilton Beckley": {
        "primary": {
          "price": 169,
          "category": "public_refundable",
          "basis": "nightly",
          "source": "ads"
        },
        "ranges": {
          "public_refundable": {
            "low": 169,
            "high": 169
          }
        },
        "expedia": null,
        "brand_strict": false,
        "debug": {
          "raw_file": "Tru_by_Hilton_Beckley_2026-06-30_city_ok_20260629T090418Z.json",
          "provider_ctx": "Booking.com | Tru by Hilton Beckley",
          "picked_from": "ads"
        }
      },
      "Fairfield Inn Beckley": {
        "primary": {
          "price": 115,
          "category": "public_refundable",
          "basis": "nightly",
          "source": "ads"
        },
        "ranges": {
          "public_refundable": {
            "low": 115,
            "high": 236
          }
        },
        "expedia": null,
        "brand_strict": false,
        "debug": {
          "raw_file": "Fairfield_Inn_Beckley_2026-06-30_addr_ok_20260629T090419Z.json",
          "provider_ctx": "Hotels.com | Quality Inn Beckley",
          "picked_from": "ads"
        }
      },
      "Best Western Beckley": "N/A",
      "Country Inn Beckley": {
        "primary": {
          "price": 114,
          "category": "public_refundable",
          "basis": "nightly",
          "source": "ads"
        },
        "ranges": {
          "public_refundable": {
            "low": 114,
            "high": 114
          }
        },
        "expedia": null,
        "brand_strict": false,
        "debug": {
          "raw_file": "Country_Inn_Beckley_2026-06-30_addr_ok_20260629T090430Z.json",
          "provider_ctx": "Booking.com | Quality Inn Beckley",
          "picked_from": "ads"
        }
      }
    },
    "Friday": {
      "Comfort Inn Beckley": {
        "primary": {
          "price": 162,
          "category": "public_refundable",
          "basis": "nightly",
          "source": "properties"
        },
        "ranges": {
          "public_refundable": {
            "low": 162,
            "high": 181
          }
        },
        "expedia": null,
        "brand_strict": true,
        "debug": {
          "raw_file": "Comfort_Inn_Beckley_2026-07-03_addr_ok_20260629T090431Z.json",
          "provider_ctx": "Comfort Inn Beckley",
          "picked_from": "properties"
        }
      },
      "Courtyard Beckley": {
        "primary": {
          "price": 180,
          "category": "public_refundable",
          "basis": "nightly",
          "source": "properties"
        },
        "ranges": {
          "public_refundable": {
            "low": 180,
            "high": 203
          }
        },
        "expedia": null,
        "brand_strict": false,
        "debug": {
          "raw_file": "Courtyard_Beckley_2026-07-03_addr_ok_20260629T090433Z.json",
          "provider_ctx": "Straightforward hotel offering contemporary rooms & a courtyard with a fire pit, plus free WiFi. | Courtyard by Marriott Beckley",
          "picked_from": "properties"
        }
      },
      "Hampton Inn Beckley": {
        "primary": {
          "price": 211,
          "category": "public_refundable",
          "basis": "nightly",
          "source": "ads"
        },
        "ranges": {
          "public_refundable": {
            "low": 211,
            "high": 211
          }
        },
        "expedia": null,
        "brand_strict": false,
        "debug": {
          "raw_file": "Hampton_Inn_Beckley_2026-07-03_addr_ok_20260629T090435Z.json",
          "provider_ctx": "Hampton Inn Beckley | Hampton Inn Beckley",
          "picked_from": "ads"
        }
      },
      "Tru by Hilton Beckley": {
        "primary": {
          "price": 183,
          "category": "public_refundable",
          "basis": "nightly",
          "source": "ads"
        },
        "ranges": {
          "public_refundable": {
            "low": 183,
            "high": 183
          }
        },
        "expedia": null,
        "brand_strict": false,
        "debug": {
          "raw_file": "Tru_by_Hilton_Beckley_2026-07-03_addr_ok_20260629T090437Z.json",
          "provider_ctx": "Booking.com | Tru by Hilton Beckley",
          "picked_from": "ads"
        }
      },
      "Fairfield Inn Beckley": {
        "primary": {
          "price": 329,
          "category": "public_refundable",
          "basis": "nightly",
          "source": "properties"
        },
        "ranges": {
          "public_refundable": {
            "low": 329,
            "high": 368
          }
        },
        "expedia": null,
        "brand_strict": false,
        "debug": {
          "raw_file": "Fairfield_Inn_Beckley_2026-07-03_addr_ok_20260629T090439Z.json",
          "provider_ctx": "Fairfield by Marriott Inn & Suites Beckley",
          "picked_from": "properties"
        }
      },
      "Best Western Beckley": {
        "primary": {
          "price": 176,
          "category": "public_refundable",
          "basis": "nightly",
          "source": "ads"
        },
        "ranges": {
          "public_refundable": {
            "low": 176,
            "high": 176
          }
        },
        "expedia": null,
        "brand_strict": false,
        "debug": {
          "raw_file": "Best_Western_Beckley_2026-07-03_addr_ok_20260629T090440Z.json",
          "provider_ctx": "Booking.com | Best Western Plus Beckley Inn",
          "picked_from": "ads"
        }
      },
      "Country Inn Beckley": {
        "primary": {
          "price": 128,
          "category": "public_refundable",
          "basis": "nightly",
          "source": "properties"
        },
        "ranges": {
          "public_refundable": {
            "low": 128,
            "high": 180
          }
        },
        "expedia": null,
        "brand_strict": false,
        "debug": {
          "raw_file": "Country_Inn_Beckley_2026-07-03_city_ok_20260629T090445Z.json",
          "provider_ctx": "Unfussy hotel offering free hot breakfast & Wi-Fi, plus an indoor/outdoor pool & an exercise room. | Country Inn & Suites by Radisson, Beckley, WV",
          "picked_from": "properties"
        }
      }
    }
  }
}